chainbase/common_lib/__init__.py
chainbase_lib-0.0.3.dist-info/METADATA
chainbase_lib-0.0.3.dist-info/WHEEL
chainbase_lib-0.0.3.dist-info/RECORD
